{
  "0e93b819cc2e8121f7281dc8e4eaaf78" : {
    "statistic" : {
      "failed" : 0,
      "broken" : 0,
      "skipped" : 0,
      "passed" : 1,
      "unknown" : 0,
      "total" : 1
    },
    "items" : [ {
      "uid" : "b1bb5ad6b6a13a3d",
      "reportUrl" : "https://PappIldiko.github.io/selenium-py-peldatar/24//#testresult/b1bb5ad6b6a13a3d",
      "status" : "passed",
      "time" : {
        "start" : 1626438355821,
        "stop" : 1626438355821,
        "duration" : 0
      }
    } ]
  },
  "753cdf21aa3257d3e2249d83346a13e6" : {
    "statistic" : {
      "failed" : 0,
      "broken" : 0,
      "skipped" : 0,
      "passed" : 1,
      "unknown" : 0,
      "total" : 1
    },
    "items" : [ {
      "uid" : "3faa293ca9aea758",
      "reportUrl" : "https://PappIldiko.github.io/selenium-py-peldatar/24//#testresult/3faa293ca9aea758",
      "status" : "passed",
      "time" : {
        "start" : 1626438355820,
        "stop" : 1626438355820,
        "duration" : 0
      }
    } ]
  },
  "77caee529814bb5616db6b28df37c87c" : {
    "statistic" : {
      "failed" : 0,
      "broken" : 0,
      "skipped" : 0,
      "passed" : 1,
      "unknown" : 0,
      "total" : 1
    },
    "items" : [ {
      "uid" : "df9eb8d0507257f5",
      "reportUrl" : "https://PappIldiko.github.io/selenium-py-peldatar/24//#testresult/df9eb8d0507257f5",
      "status" : "passed",
      "time" : {
        "start" : 1626438355818,
        "stop" : 1626438355819,
        "duration" : 1
      }
    } ]
  },
  "0cc1fa42e1c19a0d3fd610d45c4ba65a" : {
    "statistic" : {
      "failed" : 0,
      "broken" : 0,
      "skipped" : 0,
      "passed" : 1,
      "unknown" : 0,
      "total" : 1
    },
    "items" : [ {
      "uid" : "d742d1a94e14adf1",
      "reportUrl" : "https://PappIldiko.github.io/selenium-py-peldatar/24//#testresult/d742d1a94e14adf1",
      "status" : "passed",
      "time" : {
        "start" : 1626438355812,
        "stop" : 1626438355812,
        "duration" : 0
      }
    } ]
  }
}